socketsundso/__init__.py
socketsundso/endpoints.py
socketsundso/handler.py
socketsundso/models.py
socketsundso-0.0.5.dist-info/LICENSE
socketsundso-0.0.5.dist-info/WHEEL
socketsundso-0.0.5.dist-info/METADATA
socketsundso-0.0.5.dist-info/RECORD
