Metadata-Version: 2.1
Name: socketsundso
Version: 0.0.5
Summary: socketsundso: A WebSocket JSON API Framework based on FastAPI, pydantic and starlette
Author-email: Markus Bach <python@dingensundso.de>
Requires-Python: >=3.10
Classifier: License :: OSI Approved :: MIT License
Classifier: Programming Language :: Python :: 3 :: Only
Classifier: Programming Language :: Python :: 3.10
Classifier: Operating System :: OS Independent
Classifier: Development Status :: 2 - Pre-Alpha
Classifier: Framework :: FastAPI
Classifier: Topic :: Internet :: WWW/HTTP
Classifier: Intended Audience :: Developers
Requires-Dist: fastapi >=0.75.1
Requires-Dist: uvicorn[standard] >=0.12.0 ; extra == "dev"
Requires-Dist: flake8 >=3.8.3 ; extra == "dev"
Requires-Dist: mypy >=0.942 ; extra == "dev"
Requires-Dist: autoflake >=1.4.0 ; extra == "dev"
Requires-Dist: black >= 22.3.0 ; extra == "dev"
Requires-Dist: isort >=5.10.0 ; extra == "dev"
Requires-Dist: pytest >=6.2.4 ; extra == "dev"
Requires-Dist: pytest-asyncio >=0.18.0 ; extra == "dev"
Requires-Dist: sphinx >= 4.5.0 ; extra == "dev"
Project-URL: documentation, https://socketsundso.dingensundso.de/
Project-URL: repository, https://github.com/dingensundso/socketsundso
Provides-Extra: dev
